easyscrape_bingsuggest/__init__.py
easyscrape_bingsuggest/querysuggestions.py
easyscrape_bingsuggest-0.1.1.dist-info/LICENSE
easyscrape_bingsuggest-0.1.1.dist-info/METADATA
easyscrape_bingsuggest-0.1.1.dist-info/WHEEL
easyscrape_bingsuggest-0.1.1.dist-info/top_level.txt
easyscrape_bingsuggest-0.1.1.dist-info/RECORD
