Metadata-Version: 2.1
Name: easyscrape-bingsuggest
Version: 0.1.1
Summary: Easy web scraping for Amazon search bar suggested terms
Home-page: https://github.com/amazingjoe/easyscrape-bingsuggest
Author: Joseph Ucuzoglu
Author-email: baldmancodes@gmail.com
Classifier: Programming Language :: Python :: 3
Classifier: License :: OSI Approved :: MIT License
Classifier: Operating System :: OS Independent
Requires-Python: >=3.7
License-File: LICENSE
